flatpages_i18n/__init__.py
flatpages_i18n/admin.py
flatpages_i18n/forms.py
flatpages_i18n/middleware.py
flatpages_i18n/models.py
flatpages_i18n/translation.py
flatpages_i18n/urls.py
flatpages_i18n/views.py
flatpages_i18n/widgets.py
flatpages_i18n/migrations/0001_initial.py
flatpages_i18n/migrations/__init__.py
flatpages_i18n/static/css/flatpages_i18n/admin.css
flatpages_i18n/static/js/flatpages_i18n/jquery-1.11.0.min.map
flatpages_i18n/static/js/flatpages_i18n/jquery.js
flatpages_i18n/templates/flatpages_i18n/default.html
flatpages_i18n/templates/flatpages_i18n/menu.html
flatpages_i18n/templatetags/__init__.py
flatpages_i18n/templatetags/flatpages_i18n.py
django_flatpages_multilanguage-0.1.0.dist-info/LICENSE
django_flatpages_multilanguage-0.1.0.dist-info/METADATA
django_flatpages_multilanguage-0.1.0.dist-info/WHEEL
django_flatpages_multilanguage-0.1.0.dist-info/top_level.txt
django_flatpages_multilanguage-0.1.0.dist-info/RECORD
