Metadata-Version: 2.1
Name: django-flatpages-multilanguage
Version: 0.1.0
Summary: Translatable flatpages
Home-page: https://github.com/PragmaticMates/django-flatpages-i18n
Author: Pragmatic Mates
Author-email: info@pragmaticmates.com
Maintainer: Pragmatic Mates
Maintainer-email: info@pragmaticmates.com
License: BSD License
Keywords: django flatpages translation i18n wysiwyg
Platform: UNKNOWN
Classifier: Programming Language :: Python
Classifier: Programming Language :: Python :: 2.5
Classifier: Programming Language :: Python :: 2.6
Classifier: Programming Language :: Python :: 2.7
Classifier: Programming Language :: Python :: 3.5
Classifier: Programming Language :: Python :: 3.6
Classifier: Operating System :: OS Independent
Classifier: Environment :: Web Environment
Classifier: Intended Audience :: Developers
Classifier: Framework :: Django
Classifier: License :: OSI Approved :: BSD License
Requires-Dist: future
Requires-Dist: django-modeltranslation
Requires-Dist: django
Requires-Dist: django-mptt
